{"Quincy Crew-simply TOOBASED": {"win_prob": 0.5, "timestamp": "2021-12-15 17:52"}, "Team Undying-Wildcard Gaming": {"win_prob": 0.5, "timestamp": "2021-12-15 17:52"}, "4 Zoomers-Black N Yellow": {"win_prob": 0.5, "timestamp": "2021-12-15 17:52"}, "Evil Geniuses-Arkosh Gaming": {"win_prob": 0.5, "timestamp": "2021-12-15 18:06"}, "Quincy Crew-4 Zoomers": {"win_prob": 0.5, "timestamp": "2021-12-15 18:06"}, "Team Undying-simply TOOBASED": {"win_prob": 0.5, "timestamp": "2021-12-15 18:20"}, "Evil Geniuses-Black N Yellow": {"win_prob": 0.5, "timestamp": "2021-12-15 18:20"}, "Arkosh Gaming-Wildcard Gaming": {"win_prob": 0.5, "timestamp": "2021-12-15 18:20"}, "Team Undying-Black N Yellow": {"win_prob": 0.5, "timestamp": "2021-12-15 18:49"}, "Quincy Crew-Arkosh Gaming": {"win_prob": 0.5, "timestamp": "2021-12-15 18:49"}, "Evil Geniuses-Wildcard Gaming": {"win_prob": 0.5, "timestamp": "2021-12-15 19:00"}, "4 Zoomers-simply TOOBASED": {"win_prob": 0.5, "timestamp": "2021-12-15 20:42"}, "Arkosh Gaming-Black N Yellow": {"win_prob": 0.5, "timestamp": "2021-12-15 20:42"}, "Quincy Crew-Wildcard Gaming": {"win_prob": 0.5, "timestamp": "2021-12-18 19:10"}, "Evil Geniuses-simply TOOBASED": {"win_prob": 0.5, "timestamp": "2021-12-18 19:10"}, "Team Undying-4 Zoomers": {"win_prob": 0.5, "timestamp": "2021-12-21 22:26"}, "Wildcard Gaming-Black N Yellow": {"win_prob": 0.5, "timestamp": "2022-01-05 15:12"}, "Arkosh Gaming-simply TOOBASED": {"win_prob": 0.5, "timestamp": "2022-01-05 15:12"}, "Evil Geniuses-4 Zoomers": {"win_prob": 0.5, "timestamp": "2022-01-08 20:04"}, "Quincy Crew-Team Undying": {"win_prob": 0.5, "timestamp": "2022-01-08 22:33"}, "Evil Geniuses-Quincy Crew": {"win_prob": 0.5, "timestamp": "2022-01-20 01:17"}, "Team Undying-Evil Geniuses": {"win_prob": 0.5, "timestamp": "2022-01-09 18:37"}, "Black N Yellow-simply TOOBASED": {"win_prob": 0.5, "timestamp": "2022-01-15 20:11"}, "Wildcard Gaming-simply TOOBASED": {"win_prob": 0.5, "timestamp": "2022-01-09 18:37"}, "Wildcard Gaming-4 Zoomers": {"win_prob": 0.5, "timestamp": "2022-01-09 18:37"}, "Arkosh Gaming-4 Zoomers": {"win_prob": 0.5, "timestamp": "2022-01-09 18:37"}, "Black N Yellow-Quincy Crew": {"win_prob": 0.5, "timestamp": "2022-01-09 18:37"}, "Arkosh Gaming-Team Undying": {"win_prob": 0.5, "timestamp": "2022-01-19 15:59"}, "5ManMidas-felt": {"win_prob": 0.5, "timestamp": "2021-12-15 17:42"}, "Team Magnus-Electronic Boys": {"win_prob": 0.5, "timestamp": "2021-12-15 17:52"}, "KBU.US-Team DogChamp": {"win_prob": 0.5, "timestamp": "2021-12-15 18:06"}, "5RATFORCESTAFF-The Cut": {"win_prob": 0.5, "timestamp": "2021-12-15 18:11"}, "Team Magnus-felt": {"win_prob": 0.5, "timestamp": "2021-12-15 18:11"}, "Electronic Boys-Team DogChamp": {"win_prob": 0.5, "timestamp": "2021-12-15 18:16"}, "5ManMidas-The Cut": {"win_prob": 0.5, "timestamp": "2021-12-15 18:20"}, "KBU.US-5RATFORCESTAFF": {"win_prob": 0.5, "timestamp": "2021-12-15 18:49"}, "felt-Electronic Boys": {"win_prob": 0.5, "timestamp": "2021-12-15 18:53"}, "Team DogChamp-5ManMidas": {"win_prob": 0.5, "timestamp": "2021-12-15 18:53"}, "Team Magnus-5RATFORCESTAFF": {"win_prob": 0.5, "timestamp": "2021-12-15 18:57"}, "The Cut-KBU.US": {"win_prob": 0.5, "timestamp": "2021-12-15 19:00"}, "Team DogChamp-felt": {"win_prob": 0.5, "timestamp": "2021-12-18 00:26"}, "5RATFORCESTAFF-5ManMidas": {"win_prob": 0.5, "timestamp": "2021-12-19 20:52"}, "The Cut-Electronic Boys": {"win_prob": 0.5, "timestamp": "2021-12-19 23:02"}, "Team Magnus-KBU.US": {"win_prob": 0.5, "timestamp": "2021-12-20 20:40"}, "Electronic Boys-5RATFORCESTAFF": {"win_prob": 0.5, "timestamp": "2021-12-22 00:24"}, "felt-The Cut": {"win_prob": 0.5, "timestamp": "2022-01-07 15:07"}, "Team Magnus-Team DogChamp": {"win_prob": 0.5, "timestamp": "2022-01-09 21:55"}, "5ManMidas-KBU.US": {"win_prob": 0.5, "timestamp": "2022-01-10 00:56"}, "Team DogChamp-The Cut": {"win_prob": 0.5, "timestamp": "2022-01-16 22:59"}, "5ManMidas-Electronic Boys": {"win_prob": 0.5, "timestamp": "2022-01-09 18:37"}, "KBU.US-Electronic Boys": {"win_prob": 0.5, "timestamp": "2022-01-09 18:37"}, "KBU.US-felt": {"win_prob": 0.5, "timestamp": "2022-01-16 22:59"}, "Team Magnus-5ManMidas": {"win_prob": 0.5, "timestamp": "2022-01-14 05:08"}, "5RATFORCESTAFF-felt": {"win_prob": 0.5, "timestamp": "2022-01-09 18:37"}, "5RATFORCESTAFF-Team DogChamp": {"win_prob": 0.5, "timestamp": "2022-01-09 18:37"}, "Team Magnus-The Cut": {"win_prob": 0.5, "timestamp": "2022-01-20 15:26"}, "Quincy Crew-Black N Yellow": {"win_prob": 0.5, "timestamp": "2022-01-11 15:04"}, "Evil Geniuses-Team Undying": {"win_prob": 0.5, "timestamp": "2022-01-12 03:13"}, "simply TOOBASED-Wildcard Gaming": {"win_prob": 0.5, "timestamp": "2022-01-12 03:13"}, "4 Zoomers-Arkosh Gaming": {"win_prob": 0.5, "timestamp": "2022-01-15 20:11"}, "4 Zoomers-Wildcard Gaming": {"win_prob": 0.5, "timestamp": "2022-01-18 15:17"}, "felt-5RATFORCESTAFF": {"win_prob": 0.5, "timestamp": "2022-01-10 14:30"}, "Electronic Boys-KBU.US": {"win_prob": 0.5, "timestamp": "2022-01-12 02:23"}, "Electronic Boys-5ManMidas": {"win_prob": 0.5, "timestamp": "2022-01-17 17:49"}, "Team DogChamp-5RATFORCESTAFF": {"win_prob": 0.5, "timestamp": "2022-01-20 15:26"}}