{"probs": {"group_rank": {"wc": [{"team": "Vici Gaming", "probs": [1.0, 0.0, 0.0, 0.0, 0.0, 0.0]}, {"team": "Team Nigma", "probs": [0.0, 1.0, 0.0, 0.0, 0.0, 0.0]}, {"team": "Invictus Gaming", "probs": [0.0, 0.0, 1.0, 0.0, 0.0, 0.0]}, {"team": "Execration", "probs": [0.0, 0.0, 0.0, 0.50156, 0.49844, 0.0]}, {"team": "Team Secret", "probs": [0.0, 0.0, 0.0, 0.49844, 0.50156, 0.0]}, {"team": "AS Monaco Gambit", "probs": [0.0, 0.0, 0.0, 0.0, 0.0, 1.0]}], "gs": [{"team": "PSG.LGD", "probs": [1.0, 0.0, 0.0, 0.0, 0.0, 0.0, 0.0, 0.0]}, {"team": "Team Nigma", "probs": [0.0, 1.0, 0.0, 0.0, 0.0, 0.0, 0.0, 0.0]}, {"team": "Vici Gaming", "probs": [0.0, 0.0, 1.0, 0.0, 0.0, 0.0, 0.0, 0.0]}, {"team": "Evil Geniuses", "probs": [0.0, 0.0, 0.0, 1.0, 0.0, 0.0, 0.0, 0.0]}, {"team": "TNC Predator", "probs": [0.0, 0.0, 0.0, 0.0, 1.0, 0.0, 0.0, 0.0]}, {"team": "Team Liquid", "probs": [0.0, 0.0, 0.0, 0.0, 0.0, 0.50022, 0.49978, 0.0]}, {"team": "Team Spirit", "probs": [0.0, 0.0, 0.0, 0.0, 0.0, 0.49978, 0.50022, 0.0]}, {"team": "beastcoast", "probs": [0.0, 0.0, 0.0, 0.0, 0.0, 0.0, 0.0, 1.0]}]}, "final_rank": [{"team": "Team Nigma", "probs": [0.0, 0.0, 0.0, 0.0, 0.0, 0.0, 0.24839, 0.12513, 0.18556, 0.09258, 0.11006, 0.11906, 0.11922]}, {"team": "T1", "probs": [0.0, 0.0, 0.0, 0.0, 0.0, 0.0, 0.24835, 0.12587, 0.18682, 0.0945, 0.10927, 0.11759, 0.1176]}, {"team": "Team Aster", "probs": [0.0, 0.0, 0.0, 0.0, 0.0, 0.0, 0.24803, 0.12523, 0.18833, 0.09447, 0.10993, 0.11628, 0.11773]}, {"team": "PSG.LGD", "probs": [0.0, 0.0, 0.0, 0.0, 0.0, 0.0, 0.24804, 0.12574, 0.18945, 0.09307, 0.10873, 0.1167, 0.11827]}, {"team": "Quincy Crew", "probs": [0.0, 0.0, 0.0, 0.0, 0.0, 0.0, 0.24936, 0.12708, 0.18599, 0.09337, 0.11008, 0.11739, 0.11673]}, {"team": "Alliance", "probs": [0.0, 0.0, 0.0, 0.0, 0.0, 0.0, 0.24977, 0.12523, 0.18831, 0.09323, 0.11037, 0.11666, 0.11643]}, {"team": "Virtus.pro", "probs": [0.0, 0.0, 0.0, 0.0, 0.0, 0.0, 0.25154, 0.12542, 0.18703, 0.09462, 0.10815, 0.11648, 0.11676]}, {"team": "NoPing e-sports", "probs": [0.0, 0.0, 0.0, 0.0, 0.0, 0.0, 0.25118, 0.12413, 0.18845, 0.09494, 0.11007, 0.11477, 0.11646]}, {"team": "Evil Geniuses", "probs": [0.0, 0.0, 0.0, 0.0, 0.0, 0.0, 0.49998, 0.24846, 0.12664, 0.06283, 0.03081, 0.01608, 0.0152]}, {"team": "Vici Gaming", "probs": [0.0, 0.0, 0.0, 0.0, 0.0, 0.0, 0.50159, 0.24929, 0.12518, 0.06119, 0.0302, 0.01716, 0.01539]}, {"team": "TNC Predator", "probs": [0.0, 0.0, 0.0, 0.0, 0.0, 0.0, 0.50065, 0.25055, 0.12473, 0.06274, 0.03017, 0.01608, 0.01508]}, {"team": "Team Liquid", "probs": [0.0, 0.0, 0.0, 0.0, 0.0, 0.49978, 0.25088, 0.1235, 0.06231, 0.03166, 0.01615, 0.00782, 0.0079]}, {"team": "Team Spirit", "probs": [0.0, 0.0, 0.0, 0.0, 0.0, 0.50022, 0.25224, 0.12437, 0.0612, 0.0308, 0.01601, 0.00793, 0.00723]}, {"team": "beastcoast", "probs": [0.0, 0.0, 0.0, 0.0, 1.0, 0.0, 0.0, 0.0, 0.0, 0.0, 0.0, 0.0, 0.0]}, {"team": "Invictus Gaming", "probs": [0.0, 0.0, 0.0, 1.0, 0.0, 0.0, 0.0, 0.0, 0.0, 0.0, 0.0, 0.0, 0.0]}, {"team": "Execration", "probs": [0.0, 0.49844, 0.50156, 0.0, 0.0, 0.0, 0.0, 0.0, 0.0, 0.0, 0.0, 0.0, 0.0]}, {"team": "Team Secret", "probs": [0.0, 0.50156, 0.49844, 0.0, 0.0, 0.0, 0.0, 0.0, 0.0, 0.0, 0.0, 0.0, 0.0]}, {"team": "AS Monaco Gambit", "probs": [1.0, 0.0, 0.0, 0.0, 0.0, 0.0, 0.0, 0.0, 0.0, 0.0, 0.0, 0.0, 0.0]}]}, "ratings": {"Evil Geniuses": "1500", "Quincy Crew": "1500", "beastcoast": "1500", "NoPing e-sports": "1500", "Team Secret": "1500", "Alliance": "1500", "Team Nigma": "1500", "Team Liquid": "1500", "Virtus.pro": "1500", "AS Monaco Gambit": "1500", "Team Spirit": "1500", "Invictus Gaming": "1500", "Team Aster": "1500", "Vici Gaming": "1500", "PSG.LGD": "1500", "T1": "1500", "TNC Predator": "1500", "Execration": "1500", "TBD": 0}, "records": {"wildcard": {"Team Secret": [0, 4, 1], "AS Monaco Gambit": [0, 3, 2], "Execration": [0, 4, 1], "Invictus Gaming": [2, 2, 1], "Vici Gaming": [2, 3, 0], "Team Nigma": [2, 2, 1]}, "group stage": {"Evil Geniuses": [1, 5, 1], "TNC Predator": [2, 3, 2], "PSG.LGD": [4, 3, 0], "beastcoast": [0, 3, 4], "Vici Gaming": [2, 4, 1], "Team Liquid": [1, 3, 3], "Team Spirit": [0, 5, 2], "Team Nigma": [4, 2, 1], "TBD": [0, 0, 0]}}, "timestamp": "2021-11-17 00:04", "n_samples": 100000, "model_version": "0.3"}