{"Lava-Infinity Esports": {"win_prob": 0.5, "timestamp": "2022-03-24 01:38"}, "beastcoast-Infinity Esports": {"win_prob": 0.5, "timestamp": "2022-03-13 21:33"}, "beastcoast-Hokori": {"win_prob": 0.5, "timestamp": "2022-03-13 21:33"}, "beastcoast-APU King Of Kings": {"win_prob": 0.5, "timestamp": "2022-03-24 01:38"}, "Infamous-Lava": {"win_prob": 0.5, "timestamp": "2022-03-24 01:38"}, "Infamous-Infinity Esports": {"win_prob": 0.5, "timestamp": "2022-03-18 02:22"}, "Hokori-Balrogs": {"win_prob": 0.5, "timestamp": "2022-03-23 02:55"}, "Thunder Awaken-Hokori": {"win_prob": 0.5, "timestamp": "2022-03-18 02:22"}, "Hokori-Infinity Esports": {"win_prob": 0.5, "timestamp": "2022-03-13 21:33"}, "Lava-Balrogs": {"win_prob": 0.5, "timestamp": "2022-03-13 21:33"}, "beastcoast-Infamous": {"win_prob": 0.5, "timestamp": "2022-03-24 01:38"}, "Thunder Awaken-Infinity Esports": {"win_prob": 0.5, "timestamp": "2022-03-24 01:38"}, "beastcoast-Lava": {"win_prob": 0.5, "timestamp": "2022-03-13 21:33"}, "Thunder Awaken-Infamous": {"win_prob": 0.5, "timestamp": "2022-03-13 21:33"}, "Thunder Awaken-Balrogs": {"win_prob": 0.5, "timestamp": "2022-03-13 21:33"}, "Infamous-APU King Of Kings": {"win_prob": 0.5, "timestamp": "2022-03-23 02:39"}, "Infamous-Hokori": {"win_prob": 0.5, "timestamp": "2022-03-24 01:38"}, "Infamous-Balrogs": {"win_prob": 0.5, "timestamp": "2022-03-13 21:33"}, "Thunder Awaken-Lava": {"win_prob": 0.5, "timestamp": "2022-03-13 21:33"}, "APU King Of Kings-Balrogs": {"win_prob": 0.5, "timestamp": "2022-03-13 21:33"}, "Thunder Awaken-APU King Of Kings": {"win_prob": 0.5, "timestamp": "2022-03-24 01:38"}, "beastcoast-Balrogs": {"win_prob": 0.5, "timestamp": "2022-03-13 21:33"}, "beastcoast-Thunder Awaken": {"win_prob": 0.5, "timestamp": "2022-03-23 02:39"}, "APU King Of Kings-Infinity Esports": {"win_prob": 0.5, "timestamp": "2022-03-13 21:33"}, "Lava-APU King Of Kings": {"win_prob": 0.5, "timestamp": "2022-03-20 15:17"}, "Hokori-Lava": {"win_prob": 0.5, "timestamp": "2022-03-23 02:55"}, "Hokori-APU King Of Kings": {"win_prob": 0.5, "timestamp": "2022-03-24 01:38"}, "Infinity Esports-Balrogs": {"win_prob": 0.5, "timestamp": "2022-03-23 02:55"}, "Team Unknown-Wolf Team": {"win_prob": 0.5, "timestamp": "2022-03-06 23:51"}, "Interitus-Inverse": {"win_prob": 0.5, "timestamp": "2022-03-06 23:51"}, "Wolf Team-SG esports": {"win_prob": 0.5, "timestamp": "2022-03-24 01:38"}, "Omega Gaming-NoPing e-sports": {"win_prob": 0.5, "timestamp": "2022-03-13 21:33"}, "SG esports-NoPing e-sports": {"win_prob": 0.5, "timestamp": "2022-03-23 02:55"}, "Team Unknown-Omega Gaming": {"win_prob": 0.5, "timestamp": "2022-03-06 23:51"}, "Inverse-Omega Gaming": {"win_prob": 0.5, "timestamp": "2022-03-06 23:51"}, "Wolf Team-NoPing e-sports": {"win_prob": 0.5, "timestamp": "2022-03-24 01:38"}, "Team Unknown-Interitus": {"win_prob": 0.5, "timestamp": "2022-03-06 23:51"}, "Omega Gaming-SG esports": {"win_prob": 0.5, "timestamp": "2022-03-24 01:38"}, "Omega Gaming-Wolf Team": {"win_prob": 0.5, "timestamp": "2022-03-13 21:33"}, "Interitus-Omega Gaming": {"win_prob": 0.5, "timestamp": "2022-03-13 21:33"}, "Team Unknown-NoPing e-sports": {"win_prob": 0.5, "timestamp": "2022-03-06 23:51"}, "Interitus-Wolf Team": {"win_prob": 0.5, "timestamp": "2022-03-24 01:38"}, "Gorillaz-Pride-NoPing e-sports": {"win_prob": 0.5, "timestamp": "2022-03-23 02:55"}, "Gorillaz-Pride-Wolf Team": {"win_prob": 0.5, "timestamp": "2022-03-13 21:33"}, "Team Unknown-Inverse": {"win_prob": 0.5, "timestamp": "2022-03-06 23:51"}, "Omega Gaming-Gorillaz-Pride": {"win_prob": 0.5, "timestamp": "2022-03-24 01:38"}, "Team Unknown-SG esports": {"win_prob": 0.5, "timestamp": "2022-03-06 23:51"}, "Inverse-NoPing e-sports": {"win_prob": 0.5, "timestamp": "2022-03-06 23:51"}, "Interitus-SG esports": {"win_prob": 0.5, "timestamp": "2022-03-13 21:33"}, "Gorillaz-Pride-SG esports": {"win_prob": 0.5, "timestamp": "2022-03-13 21:33"}, "Interitus-Gorillaz-Pride": {"win_prob": 0.5, "timestamp": "2022-03-13 21:33"}, "Team Unknown-Gorillaz-Pride": {"win_prob": 0.5, "timestamp": "2022-03-06 23:51"}, "Inverse-Gorillaz-Pride": {"win_prob": 0.5, "timestamp": "2022-03-06 23:51"}, "Inverse-SG esports": {"win_prob": 0.5, "timestamp": "2022-03-06 23:51"}, "Interitus-NoPing e-sports": {"win_prob": 0.5, "timestamp": "2022-03-13 21:33"}, "Inverse-Wolf Team": {"win_prob": 0.5, "timestamp": "2022-03-06 23:51"}, "Vendetta eSports-Wolf Team": {"win_prob": 0.5, "timestamp": "2022-03-13 17:39"}, "Ravens-SG esports": {"win_prob": 0.5, "timestamp": "2022-03-13 21:33"}, "Vendetta eSports-Ravens": {"win_prob": 0.5, "timestamp": "2022-03-13 17:39"}, "Vendetta eSports-SG esports": {"win_prob": 0.5, "timestamp": "2022-03-13 17:39"}, "Vendetta eSports-Interitus": {"win_prob": 0.5, "timestamp": "2022-03-13 17:39"}, "Vendetta eSports-Gorillaz-Pride": {"win_prob": 0.5, "timestamp": "2022-03-13 17:39"}, "Ravens-Gorillaz-Pride": {"win_prob": 0.5, "timestamp": "2022-03-13 21:33"}, "Ravens-Omega Gaming": {"win_prob": 0.5, "timestamp": "2022-03-13 21:33"}, "Interitus-Ravens": {"win_prob": 0.5, "timestamp": "2022-03-24 01:38"}, "Ravens-Wolf Team": {"win_prob": 0.5, "timestamp": "2022-03-24 01:38"}, "Ravens-NoPing e-sports": {"win_prob": 0.5, "timestamp": "2022-03-13 21:33"}, "Vendetta eSports-Omega Gaming": {"win_prob": 0.5, "timestamp": "2022-03-13 17:39"}, "Vendetta eSports-NoPing e-sports": {"win_prob": 0.5, "timestamp": "2022-03-13 17:39"}, "Dreamers-Omega Gaming": {"win_prob": 0.5, "timestamp": "2022-03-13 21:33"}, "Dreamers-SG esports": {"win_prob": 0.5, "timestamp": "2022-03-13 21:33"}, "Dreamers-Interitus": {"win_prob": 0.5, "timestamp": "2022-03-24 01:38"}, "Dreamers-Wolf Team": {"win_prob": 0.5, "timestamp": "2022-03-13 21:33"}, "Dreamers-Gorillaz-Pride": {"win_prob": 0.5, "timestamp": "2022-03-13 21:33"}, "Dreamers-NoPing e-sports": {"win_prob": 0.5, "timestamp": "2022-03-13 21:33"}, "Dreamers-Ravens": {"win_prob": 0.5, "timestamp": "2022-03-24 01:38"}, "Balrogs-beastcoast": {"win_prob": 0.5, "timestamp": "2022-03-17 02:58"}, "Infinity Esports-beastcoast": {"win_prob": 0.5, "timestamp": "2022-03-20 15:17"}, "Lava-Thunder Awaken": {"win_prob": 0.5, "timestamp": "2022-03-24 01:38"}, "Balrogs-APU King Of Kings": {"win_prob": 0.5, "timestamp": "2022-03-24 01:38"}, "Hokori-beastcoast": {"win_prob": 0.5, "timestamp": "2022-03-24 01:38"}, "Balrogs-Thunder Awaken": {"win_prob": 0.5, "timestamp": "2022-03-24 01:38"}, "Infinity Esports-APU King Of Kings": {"win_prob": 0.5, "timestamp": "2022-03-24 01:38"}, "Lava-beastcoast": {"win_prob": 0.5, "timestamp": "2022-03-24 01:38"}, "Balrogs-Infamous": {"win_prob": 0.5, "timestamp": "2022-03-24 01:38"}, "Balrogs-Lava": {"win_prob": 0.5, "timestamp": "2022-03-24 01:38"}, "Infinity Esports-Hokori": {"win_prob": 0.5, "timestamp": "2022-03-24 01:38"}, "Infamous-Thunder Awaken": {"win_prob": 0.5, "timestamp": "2022-03-24 01:38"}, "Thunder Awaken-beastcoast": {"win_prob": 0.5, "timestamp": "2022-03-24 01:38"}, "Balrogs-Hokori": {"win_prob": 0.5, "timestamp": "2022-03-24 01:38"}, "Infamous-beastcoast": {"win_prob": 0.5, "timestamp": "2022-03-23 02:55"}, "APU King Of Kings-Infamous": {"win_prob": 0.5, "timestamp": "2022-03-24 01:38"}, "NoPing e-sports-Dreamers": {"win_prob": 0.5, "timestamp": "2022-03-15 00:29"}, "SG esports-Ravens": {"win_prob": 0.5, "timestamp": "2022-03-17 02:58"}, "Gorillaz-Pride-Interitus": {"win_prob": 0.5, "timestamp": "2022-03-17 02:58"}, "Wolf Team-Omega Gaming": {"win_prob": 0.5, "timestamp": "2022-03-19 00:44"}, "NoPing e-sports-Ravens": {"win_prob": 0.5, "timestamp": "2022-03-20 15:17"}, "SG esports-Interitus": {"win_prob": 0.5, "timestamp": "2022-03-22 02:52"}, "Wolf Team-Gorillaz-Pride": {"win_prob": 0.5, "timestamp": "2022-03-24 01:38"}, "Omega Gaming-Dreamers": {"win_prob": 0.5, "timestamp": "2022-03-24 01:38"}, "NoPing e-sports-Interitus": {"win_prob": 0.5, "timestamp": "2022-03-24 01:38"}, "Gorillaz-Pride-Dreamers": {"win_prob": 0.5, "timestamp": "2022-03-24 01:38"}, "Omega Gaming-Ravens": {"win_prob": 0.5, "timestamp": "2022-03-24 01:38"}, "SG esports-Dreamers": {"win_prob": 0.5, "timestamp": "2022-03-24 01:38"}, "Omega Gaming-Interitus": {"win_prob": 0.5, "timestamp": "2022-03-24 01:38"}, "Gorillaz-Pride-Ravens": {"win_prob": 0.5, "timestamp": "2022-03-24 01:38"}, "Wolf Team-Dreamers": {"win_prob": 0.5, "timestamp": "2022-03-24 01:38"}, "NoPing e-sports-Omega Gaming": {"win_prob": 0.5, "timestamp": "2022-03-24 01:38"}, "SG esports-Gorillaz-Pride": {"win_prob": 0.5, "timestamp": "2022-03-24 01:38"}, "Wolf Team-Interitus": {"win_prob": 0.5, "timestamp": "2022-03-23 02:55"}, "Ravens-Dreamers": {"win_prob": 0.5, "timestamp": "2022-03-23 02:55"}, "NoPing e-sports-SG esports": {"win_prob": 0.5, "timestamp": "2022-03-24 01:38"}, "SG esports-Omega Gaming": {"win_prob": 0.5, "timestamp": "2022-03-23 02:39"}, "Gorillaz-Pride-Omega Gaming": {"win_prob": 0.5, "timestamp": "2022-03-23 02:39"}, "Wolf Team-Ravens": {"win_prob": 0.5, "timestamp": "2022-03-22 02:52"}, "Balrogs-Infinity Esports": {"win_prob": 0.5, "timestamp": "2022-03-24 01:38"}, "Infinity Esports-Lava": {"win_prob": 0.5, "timestamp": "2022-03-23 02:39"}, "Interitus-Dreamers": {"win_prob": 0.5, "timestamp": "2022-03-23 02:55"}, "APU King Of Kings-Thunder Awaken": {"win_prob": 0.5, "timestamp": "2022-03-23 02:55"}, "Lava-Hokori": {"win_prob": 0.5, "timestamp": "2022-03-24 01:38"}, "NoPing e-sports-Gorillaz-Pride": {"win_prob": 0.5, "timestamp": "2022-03-24 01:38"}}